cydrowinparser/LICENSE
cydrowinparser/README.MD
cydrowinparser/__init__.py
cydrowinparser/cywinparser.pyx
cydrowinparser/cywinparser_compile.py
cydrowinparser/requirements.txt
cydrowinparser/thirdparty.json
cydrowinparser-0.10.dist-info/LICENSE.rst
cydrowinparser-0.10.dist-info/METADATA
cydrowinparser-0.10.dist-info/WHEEL
cydrowinparser-0.10.dist-info/top_level.txt
cydrowinparser-0.10.dist-info/RECORD
