Metadata-Version: 2.1
Name: cydrowinparser
Version: 0.10
Summary: window dump parser for Android
Home-page: https://github.com/hansalemaos/cydrowinparser
Author: Johannes Fischer
Author-email: aulasparticularesdealemaosp@gmail.com
License: MIT
Keywords: dump
Classifier: Development Status :: 4 - Beta
Classifier: Programming Language :: Python :: 3 :: Only
Classifier: Programming Language :: Python :: 3.10
Classifier: Topic :: Software Development :: Libraries :: Python Modules
Classifier: Topic :: Utilities
License-File: LICENSE.rst
Requires-Dist: Cython
Requires-Dist: adbshellexecuter
Requires-Dist: cythondfprint
Requires-Dist: cythonevparser
Requires-Dist: exceptdrucker
Requires-Dist: numpy
Requires-Dist: pandas
Requires-Dist: regex
Requires-Dist: setuptools
